[{"id":8395,"key":"","name":"Blend Off!","transformed_name":"blend off!","boardgame_name":"Blend Off!","preview":"https://cf.geekdo-images.com/Ivrg9DdpRHt6WzhnOUQhkw__micro/img/1hehoWcS9JziutjhM4UHdcWA9ws=/fit-in/64x64/filters:strip_icc()/pic2936691.png","store_id":7,"store_thumb":"https://meeple-planet.com/wp-content/uploads/2020/03/box-front-1-200x200.jpg","price":15.5,"stock":0,"url":"https://meeple-planet.com/blend-off/","ignored":false},{"id":11454,"key":"","name":"Blend Off!","transformed_name":"blend off!","boardgame_name":"Blend Off!","preview":"https://cf.geekdo-images.com/Ivrg9DdpRHt6WzhnOUQhkw__micro/img/1hehoWcS9JziutjhM4UHdcWA9ws=/fit-in/64x64/filters:strip_icc()/pic2936691.png","store_id":4,"store_thumb":"https://www.thegamerules.com/image/cache/transparent-395x395.png","price":25.65,"stock":2,"url":"https://www.thegamerules.com/epitrapezia-paixnidia/blend-off","ignored":false}]