[{"id":15004,"key":"","name":"New York Slice","transformed_name":"new york slice","boardgame_name":"New York Slice","preview":"https://cf.geekdo-images.com/pqJB3ccbvCW4Fii-uQG1kA__micro/img/VXswNRdEaJyW2JHGme-1BsEdRe4=/fit-in/64x64/filters:strip_icc()/pic3211823.jpg","store_id":3,"store_thumb":"","price":30,"stock":2,"url":"https://www.mystery-bay.com/product-page/new-york-slice","ignored":false},{"id":9214,"key":"","name":"New York Slice","transformed_name":"new york slice","boardgame_name":"New York Slice","preview":"https://cf.geekdo-images.com/pqJB3ccbvCW4Fii-uQG1kA__micro/img/VXswNRdEaJyW2JHGme-1BsEdRe4=/fit-in/64x64/filters:strip_icc()/pic3211823.jpg","store_id":7,"store_thumb":"https://meeple-planet.com/wp-content/uploads/2019/07/box-11-200x200.jpg","price":30,"stock":2,"url":"https://meeple-planet.com/new-york-slice/","ignored":false}]