[{"id":12108,"key":"","name":"The Arrival","transformed_name":"the arrival","boardgame_name":"The Arrival","store_id":10,"store_thumb":"https://meepleonboard.gr/wp-content/uploads/2019/06/The-Arrival-510x600.png","price":30,"stock":0,"url":"https://meepleonboard.gr/shop/board-games/strategy/the-arrival/"},{"id":2163,"key":"","name":"The Arrival","transformed_name":"the arrival","boardgame_name":"The Arrival","store_id":8,"store_thumb":"https://static.efantasy.gr/products/117370/117370-0-0500-the-arrival.jpg","price":39.99,"stock":2,"url":"https://www.efantasy.gr/en/products/board-games/117370-the-arrival"}]