[{"id":12427,"key":"","name":"Colonial Twilight","transformed_name":"colonial twilight","boardgame_name":"Colonial Twilight: The French-Algerian War, 1954-62","store_id":4,"store_thumb":"https://www.thegamerules.com/image/cache/catalog/product/colonialtwilight-250x250.png","price":69.99,"stock":0,"url":"https://www.thegamerules.com/epitrapezia-paixnidia/colonial-twilight-detail"},{"id":2396,"key":"","name":"Colonial Twilight: The French-Algerian War, 1954-62","transformed_name":"colonial twilight  the french algerian war  1954 62","boardgame_name":"Colonial Twilight: The French-Algerian War, 1954-62","store_id":5,"store_thumb":"https://store.v-games.gr/wp-content/uploads/2022/01/Colonial-Twilight-The-French-Algerian-War-1954-62-324x436.jpg","price":70,"stock":0,"url":"https://store.v-games.gr/product/colonial-twilight-the-french-algerian-war-1954-62/"},{"id":9235,"key":"","name":"COLONIAL TWILIGHT","transformed_name":"colonial twilight","boardgame_name":"Colonial Twilight: The French-Algerian War, 1954-62","store_id":9,"store_thumb":"https://kaissa.gr/pub/media/catalog/product/cache/40839b2953d2ba4cdf07b38b981ce6be/p/i/pic3466068.jpg","price":95,"stock":0,"url":"https://kaissagames.com/b2c_gr/colonial-twilight.html"}]