[{"id":7389,"cr_date":"2022-04-05T21:04:24+03:00","name":"Skytear: The Breach (Exp)","boardgame_name":"Skytear: The Breach","thumb":"https://cf.geekdo-images.com/xAENRSa6wq_NCJHZXoLiXA__micro/img/EN7ESj1q8Jz4w1AnPMwKQLWUDBc=/fit-in/64x64/filters:strip_icc()/pic6098803.jpg","store_id":4,"store_thumb":"https://www.thegamerules.com/image/cache/catalog/Products%20NEW/The%20Breach%20Expansion%201-250x250.jpg","price":22.9,"stock":false,"url":"https://www.thegamerules.com/epitrapezia-paixnidia/skytear-the-breach-exp","rank":0}]