{"key":"","name":"Star Wars Rebellion","transformed_name":"star wars rebellion","boardgame_id":187645,"boardgame_name":"Star Wars: Rebellion","preview":"https://cf.geekdo-images.com/7SrPNGBKg9IIsP4UQpOi8g__micro/img/nEvTiCkWpT-ymH4bstc9c335TtQ=/fit-in/64x64/filters:strip_icc()/pic4325841.jpg","store_id":5,"store_thumb":"https://store.v-games.gr/wp-content/uploads/2019/01/Star-Wars-Rebellion-2-324x324.jpg","price":120,"stock":2,"url":"https://store.v-games.gr/product/star-wars-rebellion/","ignored":false}