{"key":"","name":"Star Wars Imperial Assault: Villain Pack - ISB Infiltrators","transformed_name":"star wars imperial assault  villain pack   isb infiltrators","boardgame_id":194902,"boardgame_name":"Star Wars: Imperial Assault – ISB Infiltrators Villain Pack","preview":"https://cf.geekdo-images.com/4RvTOgjxKqwn8NsAZrNV4Q__micro/img/lChwFFqjnrT239bocZaDDy0ucVY=/fit-in/64x64/filters:strip_icc()/pic3013569.png","store_id":3,"store_thumb":"https://static.wixstatic.com/media/9dcd7c_dce78d26821a4b1cb2b4966bc45606a2~mv2.png","price":14,"stock":2,"url":"https://www.mystery-bay.com/product-page/star-wars-imperial-assault-villain-pack-isb-infiltrators"}