{"key":"","name":"Ravensburger Επιτραπέζιο: Minecraft Expansion (26869)","transformed_name":"ravensburger   minecraft  ","boardgame_id":301055,"boardgame_name":"Minecraft: Farmer's Market Expansion","preview":"https://cf.geekdo-images.com/Oxh-Hd3rmBkvthbH_zAflg__micro/img/Hyd_hznVHpFiQIoIvMvgDUSJtnw=/fit-in/64x64/filters:strip_icc()/pic5657382.jpg","store_id":22,"store_thumb":"https://ti.gameexplorers.gr/ravensburger-epitrapezio-minecraft-expansion-26869.jpg","price":21.55,"stock":0,"url":"https://www.gameexplorers.gr/6092969/ravensburger-epitrapezio-minecraft-expansion-26869.html","ignored":false}