{"cr_date":"2022-04-12T21:35:07+03:00","name":"Bardsung: Legend of the Ancient Forge (Core Game)","boardgame_id":322524,"boardgame_name":"Bardsung","thumb":"https://cf.geekdo-images.com/g3ge0tvUBJZLQbtdDIY-Zg__micro/img/aqbIglxTu52h2uem5UvBeMV72zk=/fit-in/64x64/filters:strip_icc()/pic6514078.png","store_id":4,"store_thumb":"https://www.thegamerules.com/image/cache/catalog/Products%20NEW/Bardsung%20Legend%20of%20the%20Ancient%20Forge%20(Core%20Game)%20RPG%201-250x250.jpg","price":185,"stock":false,"url":"https://www.thegamerules.com/epitrapezia-paixnidia/bardsung-legend-of-the-ancient-forge-core-game","rank":11217}