{"key":"","name":"Exit: Το Αρχοντικό Του Τρόμου","transformed_name":"exit  το αρχοντικό του τρόμου","boardgame_id":226520,"boardgame_name":"Exit: The Game – The Sinister Mansion","preview":"https://cf.geekdo-images.com/VngJ1B6if4rE9X9OS1N8CQ__micro/img/UbN-fzib5PrsMTS0AxXlTri9j44=/fit-in/64x64/filters:strip_icc()/pic3958803.jpg","store_id":23,"store_thumb":"https://cdn.shopify.com/s/files/1/0571/7075/5773/products/EXIT_1.jpg?v=1629141559","price":14.99,"stock":0,"url":"https://hobbytheory.myshopify.com/products/exit-το-αρχοντικο-του-τρομου"}