{"key":"","name":"Anachrony: Fractures of Time (Exp)","transformed_name":"anachrony  fractures of time","boardgame_id":272077,"boardgame_name":"Anachrony: Fractures of Time","preview":"https://cf.geekdo-images.com/coeTqbybidQJlx8Xwp_tHA__micro/img/4mxQGHf28Pn9bvN3BtzvSEFqGp4=/fit-in/64x64/filters:strip_icc()/pic4924713.jpg","store_id":4,"store_thumb":"https://www.thegamerules.com/image/cache/catalog/Products%20NEW/Anachrony%20Fractures%20of%20Time%201-395x395.jpg","price":45.99,"stock":0,"url":"https://www.thegamerules.com/epitrapezia-paixnidia/anachrony-fractures-of-time-exp","ignored":false}