{"key":"","name":"Ιστορίες Μυστηρίου – Αληθινά Εγκλήματα","transformed_name":"ιστορίες μυστηρίου   αληθινά εγκλήματα","boardgame_id":57052,"boardgame_name":"Black Stories: Real Crime Edition","preview":"https://cf.geekdo-images.com/ULEdZW5TN7tPUJdSzgkNxA__micro/img/wVFDT-9L3PSeA6io91LVMXC02E8=/fit-in/64x64/filters:strip_icc()/pic628278.jpg","store_id":25,"store_thumb":"https://avalongames.gr/image/cache/catalog/data/KA112714_Ιστορίες_Μυστηρίου_Αληθινά_Εγκλήματα-250x250h.jpeg","price":9.99,"stock":0,"url":"https://avalongames.gr/index.php?route=product/product&path=59&product_id=2345&limit=100"}