{"key":"","name":"Exit: The Game – Η Εγκαταλελειμμένη Καλύβα","transformed_name":"exit  the game   η εγκαταλελειμμένη καλύβα","boardgame_id":203420,"boardgame_name":"Exit: The Game – The Abandoned Cabin","store_id":15,"store_thumb":"https://storage.googleapis.com/epitrapezio-site-media/epitrapez.io/wp/20200218161809_kaissa_exit_i_egataleleimmeni_kalyva-300x417.jpeg","price":13.99,"stock":0,"url":"https://epitrapez.io/shop/epitrapezia/ellinika/exit-the-game-%ce%b7-%ce%b5%ce%b3%ce%ba%ce%b1%cf%84%ce%b1%ce%bb%ce%b5%ce%bb%ce%b5%ce%b9%ce%bc%ce%bc%ce%ad%ce%bd%ce%b7-%ce%ba%ce%b1%ce%bb%cf%8d%ce%b2%ce%b1/"}