{"key":"","name":"Final Girl: Frightmare on Maple Lane","transformed_name":"final girl  frightmare on maple lane","boardgame_id":310175,"boardgame_name":"Final Girl: Frightmare on Maple Lane","preview":"https://cf.geekdo-images.com/HpagTIwNL4QQFHhe-1szYQ__micro/img/JZzYZ_mKDY4GLEDPTkhAh7InG7A=/fit-in/64x64/filters:strip_icc()/pic6520330.jpg","store_id":7,"store_thumb":"https://meeple-planet.com/wp-content/uploads/2022/06/finalmaple-200x200.jpg","price":21.95,"stock":0,"url":"https://meeple-planet.com/final-girl-frightmare-on-maple-lane/","ignored":false}