{"cr_date":"2022-04-11T11:16:33+03:00","name":"Κατσαριδοσαλάτα","boardgame_id":32341,"boardgame_name":"Cockroach Salad","thumb":"https://cf.geekdo-images.com/RTPjvs-e_CR8twqHhHyqYw__micro/img/w-2gCyoLzmMHK-PgtDc7ovHcqqI=/fit-in/64x64/filters:strip_icc()/pic2303528.jpg","store_id":8,"store_thumb":"https://static.efantasy.gr/products/70233/70233-0-0250-katsaridosalata.jpg","price":10.79,"stock":true,"url":"https://www.efantasy.gr/en/products/board-games/70233-%CE%BA%CE%B1%CF%84%CF%83%CE%B1%CF%81%CE%B9%CE%B4%CE%BF%CF%83%CE%B1%CE%BB%CE%AC%CF%84%CE%B1","rank":3232}