{"key":"","name":"Wayfarers of the South Tigris","transformed_name":"wayfarers of the south tigris","boardgame_id":350316,"boardgame_name":"Wayfarers of the South Tigris","preview":"https://cf.geekdo-images.com/1dO66KB0b64xdbdHqf_UZg__micro/img/Uv3SeoiHLFBa_P99Xi_aMD8HDsQ=/fit-in/64x64/filters:strip_icc()/pic6484574.png","store_id":4,"store_thumb":"https://www.thegamerules.com/image/cache/catalog/Products%20NEW/wayfarers%20of%20the%20south%20tigris-xml-250x250.PNG","price":54.9,"stock":2,"url":"https://www.thegamerules.com/epitrapezia-paixnidia/wayfarers-of-the-south-tigris","ignored":false}