{"cr_date":"2022-04-05T21:03:43+03:00","name":"FFG – Arkham Horror LCG: Stella Clark Investigator Deck (Expansion)","boardgame_id":305518,"boardgame_name":"Arkham Horror: The Card Game – Stella Clark: Investigator Starter Deck","thumb":"https://cf.geekdo-images.com/aNMd5bJ29wISodVT47T4rw__micro/img/O5MKbnxZoE8knpmWiLMviI3Fles=/fit-in/64x64/filters:strip_icc()/pic5304387.png","store_id":15,"store_thumb":"https://storage.googleapis.com/epitrapezio-site-media/epitrapez.io/wp/stella-clarck.jpeg","price":19.99,"stock":true,"url":"https://epitrapez.io/product/ffg-arkham-horror-lcg-stella-clark-investigator-deck/","rank":0}