{"key":"","name":"Concordia : Salsa (expansion)","transformed_name":"concordia   salsa","boardgame_id":181084,"boardgame_name":"Concordia: Salsa","preview":"https://cf.geekdo-images.com/-4HtbGtzFMC14laR8Azj9Q__micro/img/gjPS-Jj9rJj6edI-XDpV-FCMS58=/fit-in/64x64/filters:strip_icc()/pic3882304.jpg","store_id":7,"store_thumb":"https://meeple-planet.com/wp-content/uploads/2022/01/front-5-200x200.jpg","price":30.99,"stock":2,"url":"https://meeple-planet.com/concordia-salsa-expansion/","ignored":false}