{"key":"","name":"Adventure Games: The Gloom City File","transformed_name":"adventure games  the gloom city file","boardgame_id":317365,"boardgame_name":"Adventure Games: The Gloom City File","preview":"https://cf.geekdo-images.com/voSgOcpYelkNfpmeQWgOAA__micro/img/S5VxhetEAL9orHmcGNmJ6OrKAj4=/fit-in/64x64/filters:strip_icc()/pic6630213.jpg","store_id":4,"store_thumb":"https://www.thegamerules.com/image/cache/catalog/Products%20NEW/adventure%20games%20the%20gloom%20city%20file-xml-395x395.PNG","price":20,"stock":0,"url":"https://www.thegamerules.com/epitrapezia-paixnidia/adventure-games-the-gloom-city-file","ignored":false}