{"key":"","name":"Tulip & Rose","transformed_name":"tulip   rose","boardgame_id":328378,"boardgame_name":"Tulip & Rose","preview":"https://cf.geekdo-images.com/tSbzV94yQHzi8MUcNaeIMg__micro/img/K7xBKTE2j6aBU8bcrGLBlmiOGMc=/fit-in/64x64/filters:strip_icc()/pic5901586.jpg","store_id":4,"store_thumb":"https://www.thegamerules.com/image/cache/catalog/Products%20NEW/tulip%20n%20rose-xml-395x395.PNG","price":22.5,"stock":2,"url":"https://www.thegamerules.com/index.php?route=product/product&path=100917&product_id=29706","ignored":false}