{"key":"","name":"WELCOME ΣΤΟ ΣΠΙΤΙ ΤΩΝ ΟΝΕΙΡΩΝ ΣΑΣ","transformed_name":"welcome στο σπιτι των ονειρων σασ","boardgame_id":233867,"boardgame_name":"Welcome To...","preview":"https://cf.geekdo-images.com/g4XmxyKhNVdhC3QPd1purQ__micro/img/nFBdWL9VzYeTpQpxfSx2OkEylaA=/fit-in/64x64/filters:strip_icc()/pic3761012.jpg","store_id":28,"store_thumb":"https://www.fantasy-shop.gr/images/thumbnails/240/240/detailed/20/welcome_.jpg","price":24.99,"stock":0,"url":"https://www.fantasy-shop.gr/welcome-sto-spiti-ton-oneiron-sas.html","ignored":false}