{"key":"","name":"Russia Besieged Deluxe","transformed_name":"russia besieged deluxe","boardgame_id":224374,"boardgame_name":"Russia Besieged: Deluxe Edition","preview":"https://cf.geekdo-images.com/zBWhZ8uIF1pZWaHUKbmVwQ__micro/img/0eDZfwAqmSSHxXDrYzjS19MMZjE=/fit-in/64x64/filters:strip_icc()/pic3494237.jpg","store_id":4,"store_thumb":"https://www.thegamerules.com/image/cache/catalog//Products%20NEW/product-32970-395x395h.png","price":103,"stock":2,"url":"https://www.thegamerules.com/index.php?route=product/product&path=100917&product_id=32970","ignored":false}