{"cr_date":"2022-04-05T21:04:01+03:00","name":"Τα 7 Θαύματα Του Κόσμου","boardgame_id":68448,"boardgame_name":"7 Wonders","thumb":"https://cf.geekdo-images.com/RvFVTEpnbb4NM7k0IF8V7A__original/img/JQvRoz0xns9LZII74-ygKGDq_Es=/0x0/filters:format(jpeg)/pic860217.jpg","store_id":15,"store_thumb":"https://storage.googleapis.com/epitrapezio-site-media/epitrapez.io/wp/20151104114516_kaissa_ta_7_thaymata_tou_kosmou-300x299.jpeg","price":32.71,"stock":false,"url":"https://epitrapez.io/product/7-%ce%b8%ce%b1%cf%8d%ce%bc%ce%b1%cf%84%ce%b1-%cf%84%ce%bf%cf%85-%ce%ba%cf%8c%cf%83%ce%bc%ce%bf%cf%85-%cf%84%ce%b1/","rank":76}