{"key":"","name":"Prehistories (GR)","transformed_name":"prehistories","boardgame_id":318183,"boardgame_name":"Prehistories","preview":"https://cf.geekdo-images.com/Obs19a307oGETkE9FQAhgg__micro/img/EuSrQPyYHooAB-f5SDGnvxZ4a2Y=/fit-in/64x64/filters:strip_icc()/pic5627203.png","store_id":4,"store_thumb":"https://www.thegamerules.com/image/cache/catalog/Products%20NEW/Prehistories%201-250x250.jpg","price":27.99,"stock":2,"url":"https://www.thegamerules.com/epitrapezia-paixnidia/prehistories-gr","ignored":false}