{"cr_date":"2022-04-12T21:35:24+03:00","name":"It's a Wonderful Kingdom","boardgame_id":327711,"boardgame_name":"It's a Wonderful Kingdom","thumb":"https://cf.geekdo-images.com/p_KiU7rgcF807gKpn8bgdw__micro/img/reUR6Pxi0Kgkhoj7GaPhji2sRjc=/fit-in/64x64/filters:strip_icc()/pic6095803.jpg","store_id":4,"store_thumb":"https://www.thegamerules.com/image/cache/catalog/Products%20NEW/It's%20a%20wonderful%20Kingdom%201-250x250.jpg","price":28.2,"stock":false,"url":"https://www.thegamerules.com/epitrapezia-paixnidia/it-s-a-wonderful-kingdom","rank":2076}