{"cr_date":"2022-04-11T11:16:10+03:00","name":"BrainBox - Φάρμα","boardgame_id":289721,"boardgame_name":"BrainBox: Farm","thumb":"https://cf.geekdo-images.com/smbRzzmBB22_GGzuY_v2YA__micro/img/uCnVOcYtCkLDrBZVBiBwblIG0jk=/fit-in/64x64/filters:strip_icc()/pic6453437.jpg","store_id":4,"store_thumb":"https://www.thegamerules.com/image/cache/catalog/Products%20NEW/ΦΑΡΜΑ%20ΕΠΙΤΡΑΠΕΖΙΟ%20ΠΑΙΧΝΙΔΙ%201-250x250.jpg","price":13.5,"stock":true,"url":"https://www.thegamerules.com/epitrapezia-paixnidia/brainbox-farma","rank":0}