{"key":"","name":"BANG! The Dice Game - Old Saloon (Exp)","transformed_name":"bang! the dice game   old saloon","boardgame_id":193614,"boardgame_name":"BANG! The Dice Game: Old Saloon","preview":"https://cf.geekdo-images.com/KWNjUZrHY9Mk_Wm7-Y6L8A__micro/img/xY0emi4zgr7gA1MkOQb5i-E0KUM=/fit-in/64x64/filters:strip_icc()/pic3068557.png","store_id":4,"store_thumb":"https://www.thegamerules.com/image/cache/catalog/Products%20NEW/Bang!%20The%20Dice%20Game%20-%20Old%20Saloon%20(Exp.)%201-250x250.jpg","price":16.48,"stock":2,"url":"https://www.thegamerules.com/epitrapezia-paixnidia/bang-the-dice-game-old-saloon-exp","ignored":false}