{"key":"","name":"TIME Stories Revolution: Experience (Exp)","transformed_name":"time stories revolution  experience","boardgame_id":284819,"boardgame_name":"TIME Stories Revolution: Experience","preview":"https://cf.geekdo-images.com/dxrNk9x7X3MuxzlUPDv7pw__micro/img/4pJZ9e6FInAxOYXjDjQ_huoQL9w=/fit-in/64x64/filters:strip_icc()/pic6124569.png","store_id":4,"store_thumb":"https://www.thegamerules.com/image/cache/transparent-395x395.png","price":20.08,"stock":2,"url":"https://www.thegamerules.com/epitrapezia-paixnidia/time-stories-revolution-experience-exp-detail","ignored":false}