{"key":"","name":"Folklore: The Affliction","transformed_name":"folklore  the affliction","boardgame_id":159504,"boardgame_name":"Folklore: The Affliction","preview":"https://cf.geekdo-images.com/7GPc68Crw-MqJHEL9k0kAA__micro/img/fjqR0CQ6gg6MSv_IHNeYl2cpkH0=/fit-in/64x64/filters:strip_icc()/pic3647804.png","store_id":7,"store_thumb":"https://meeple-planet.com/wp-content/uploads/2021/03/folklore-200x200.jpg","price":65.97,"stock":2,"url":"https://meeple-planet.com/folklore-the-affliction/","ignored":false}