{"key":"","name":"Vault Assault","transformed_name":"vault assault","boardgame_id":226757,"boardgame_name":"Vault Assault","preview":"https://cf.geekdo-images.com/bpCqgLuXxkoCWJ4SiHHH1Q__micro/img/YLCmQF2djjpuJKVYGNjV9zdqWXg=/fit-in/64x64/filters:strip_icc()/pic3737221.png","store_id":4,"store_thumb":"https://www.thegamerules.com/image/cache/catalog/product/boomerangbox1-395x395.png","price":21,"stock":2,"url":"https://www.thegamerules.com/index.php?route=product/product&path=100917&product_id=12470","ignored":false}