{"key":"","name":"3 Laws of Robotics","transformed_name":"3 laws of robotics","boardgame_id":271447,"boardgame_name":"3 Laws of Robotics","preview":"https://cf.geekdo-images.com/LGUz2_a11aGZavYZvakJjA__micro/img/etWFNxqhFHYAQjHSy1Fb9M6YPcM=/fit-in/64x64/filters:strip_icc()/pic4559202.png","store_id":4,"store_thumb":"https://www.thegamerules.com/image/cache/catalog/Products%20NEW/3%20Laws%20of%20Robotics%201-395x395.jpg","price":14.16,"stock":1,"url":"https://www.thegamerules.com/epitrapezia-paixnidia/3-laws-of-robotics","ignored":false}