{"cr_date":"2022-04-12T21:35:22+03:00","name":"Red Flag Over Paris","boardgame_id":296577,"boardgame_name":"Red Flag Over Paris","thumb":"https://cf.geekdo-images.com/xpvbP6BfHoR9GdW7Dpg8hA__micro/img/QsKmbtJLkYNTIKUPlGSgToA6xlI=/fit-in/64x64/filters:strip_icc()/pic6205682.png","store_id":4,"store_thumb":"https://www.thegamerules.com/image/cache/catalog/Products%20NEW/Red%20Flag%20Over%20Paris%201-250x250.jpg","price":39.99,"stock":false,"url":"https://www.thegamerules.com/epitrapezia-paixnidia/red-flag-over-paris","rank":5055}