{"cr_date":"2022-04-05T21:05:05+03:00","name":"Recollect – Ταξίδι Στο Χρόνο","boardgame_id":183051,"boardgame_name":"Travel in Time","thumb":"https://cf.geekdo-images.com/sGRVV06M6vXi8cBNRaGezw__micro/img/xSZVpDXUsfAGpxyOjl1VplGluwA=/fit-in/64x64/filters:strip_icc()/pic2644992.jpg","store_id":4,"store_thumb":"https://www.thegamerules.com/image/cache/catalog/Products%20NEW/Recollect_–_Ταξίδι_Στο_Χρόνο-250x250.jpg","price":16,"stock":false,"url":"https://www.thegamerules.com/epitrapezia-paixnidia/recollect-taksidi-sto-xrono","rank":0}