{"key":"","name":"Small World: Sky Islands (Exp)","transformed_name":"small world  sky islands","boardgame_id":235520,"boardgame_name":"Small World: Sky Islands","preview":"https://cf.geekdo-images.com/OvXNcK_y4FY_0luh8xF3dQ__micro/img/K5VqAn9-N2DEXlrTgOVp9wD3LC0=/fit-in/64x64/filters:strip_icc()/pic3740948.jpg","store_id":4,"store_thumb":"https://www.thegamerules.com/image/cache/catalog/Products%20NEW/Small-World-Sky-Islands-(Exp)-0-395x395.jpg","price":29.43,"stock":2,"url":"https://www.thegamerules.com/epitrapezia-paixnidia/small-world-sky-islands-exp","ignored":false}