{"cr_date":"2022-04-11T11:18:01+03:00","name":"SPACE GATE ODYSSEY","boardgame_id":266179,"boardgame_name":"Space Gate Odyssey","thumb":"https://cf.geekdo-images.com/oXSexkDmjfkaomjkUzUI3Q__micro/img/V_jFATDK47yfMszmxJ2efkwZfRM=/fit-in/64x64/filters:strip_icc()/pic4924648.jpg","store_id":9,"store_thumb":"https://kaissa.gr/pub/media/catalog/product/cache/40839b2953d2ba4cdf07b38b981ce6be/p/i/pic4435105.png","price":77,"stock":true,"url":"https://kaissagames.com/b2c_gr/space-gate-odyssey.html","rank":2872}