{"key":"","name":"ARCADIA QUEST: RIDERS","transformed_name":"arcadia quest  riders","boardgame_id":233917,"boardgame_name":"Arcadia Quest: Riders","preview":"https://cf.geekdo-images.com/EZD0iYDu9OFuJ0JUxq9k_Q__micro/img/eIHqX6dOn0f1yzgb4QBRTRgCu90=/fit-in/64x64/filters:strip_icc()/pic4171325.jpg","store_id":9,"store_thumb":"https://kaissa.gr/pub/media/catalog/product/cache/40839b2953d2ba4cdf07b38b981ce6be/p/i/pic4171325.jpg","price":65,"stock":0,"url":"https://kaissagames.com/b2c_gr/arcadia-quest-riders.html","ignored":false}