{"cr_date":"2022-04-05T21:05:02+03:00","name":"Guns&Steel : A Civilization Card Game","boardgame_id":211323,"boardgame_name":"Im Wandel der Zeiten: Das Kartenspiel","thumb":"https://cf.geekdo-images.com/VjmTxb2QgnEXqhlk8dN85Q__micro/img/6wfUCp2dBk21ozawxI5JTsvupOU=/fit-in/64x64/filters:strip_icc()/pic3376945.jpg","store_id":7,"store_thumb":"https://meeple-planet.com/wp-content/uploads/2019/08/box-3-200x200.jpg","price":15,"stock":true,"url":"https://meeple-planet.com/shop/gunssteel-a-civilization-card-game/","rank":0}