{"key":"","name":"Wayfinders","transformed_name":"wayfinders","boardgame_id":286156,"boardgame_name":"Wayfinders","preview":"https://cf.geekdo-images.com/noSYAlSZ0f0SErWFjv7IZA__micro/img/_Rfk9t-qVINrQJPQOJacR2oQkpI=/fit-in/64x64/filters:strip_icc()/pic4883489.png","store_id":4,"store_thumb":"https://www.thegamerules.com/image/cache/catalog/Products%20NEW/Wayfinders-395x395.jpg","price":37,"stock":2,"url":"https://www.thegamerules.com/index.php?route=product/product&path=100917&product_id=14773","ignored":false}