[{"id":5266,"key":"","name":"Star Wars Legion: BX-series Droid Commandos Unit Expansion","transformed_name":"star wars legion  bx series droid commandos unit  ","boardgame_name":"Star Wars: Legion – BX-series Droid Commandos Unit Expansion","preview":"https://cf.geekdo-images.com/sGtZ-w2j13MEyKbV_HS9ig__micro/img/bPVRsgSgCHkyfabqSUBPXkZFQcM=/fit-in/64x64/filters:strip_icc()/pic5307099.png","store_id":4,"store_thumb":"https://www.thegamerules.com/image/cache/catalog/Products%20NEW/FFG%20-%20Star%20Wars%20Legion%20BX-series%20Droid%20Commandos%20Unit%20Expansion%20%201-250x250.jpg","price":37.99,"stock":2,"url":"https://www.thegamerules.com/epitrapezia-paixnidia/star-wars-legion-bx-series-droid-commandos-unit-expansion","ignored":false}]