[{"id":11884,"key":"","name":"Star Wars: Imperial Assault – Echo Base Troopers Ally Pack","transformed_name":"star wars  imperial assault   echo base troopers ally pack","boardgame_name":"Star Wars: Imperial Assault – Echo Base Troopers Ally Pack","preview":"https://cf.geekdo-images.com/VVTrrAsEXGXNaTEu8DRm4A__micro/img/GYWjKmB5hWBIfXsuiVED1VCyL8w=/fit-in/64x64/filters:strip_icc()/pic2786298.jpg","store_id":5,"store_thumb":"","price":16.5,"stock":2,"url":"https://store.v-games.gr/product/star-wars-imperial-assault-echo-base-troopers-ally-pack/","ignored":false}]