[{"id":13901,"key":"","name":"Arkham Horror LCG: In Too Deep (Exp)","transformed_name":"arkham horror   in too deep","boardgame_name":"Arkham Horror: The Card Game – In Too Deep: Mythos Pack","preview":"https://cf.geekdo-images.com/gORqSOGWBMOAbyA2feP8Cg__micro/img/Kc5qLZxSii1mr8PeRxEwREuYaGs=/fit-in/64x64/filters:strip_icc()/pic5632715.png","store_id":4,"store_thumb":"https://www.thegamerules.com/image/cache/catalog/Products%20NEW/Arkham-Horror-LCG-In-Too-Deep-(Exp)-0-395x395.jpg","price":16.28,"stock":1,"url":"https://www.thegamerules.com/epitrapezia-paixnidia/arkham-horror-lcg-in-too-deep-exp","ignored":false},{"id":8531,"key":"","name":"Arkham Horror: The Card Game – In Too Deep: Mythos Pack","transformed_name":"arkham horror  the card game   in too deep  mythos pack","boardgame_name":"Arkham Horror: The Card Game – In Too Deep: Mythos Pack","preview":"https://cf.geekdo-images.com/gORqSOGWBMOAbyA2feP8Cg__micro/img/Kc5qLZxSii1mr8PeRxEwREuYaGs=/fit-in/64x64/filters:strip_icc()/pic5632715.png","store_id":5,"store_thumb":"","price":17,"stock":0,"url":"https://store.v-games.gr/product/arkham-horror-the-card-game-in-too-deep-mythos-pack/","ignored":false}]