[{"id":6212,"key":"","name":"World of Tanks Miniatures Game","transformed_name":"world of tanks miniatures game","boardgame_name":"World of Tanks Miniatures Game","store_id":10,"store_thumb":"https://meepleonboard.gr/wp-content/uploads/2021/02/World-of-Tanks-Miniatures-Game-510x600.png","price":30,"stock":2,"url":"https://meepleonboard.gr/shop/board-games/strategy/world-of-tanks-miniatures-game/"},{"id":8735,"key":"","name":"World Of Tanks Miniatures Game","transformed_name":"world of tanks miniatures game","boardgame_name":"World of Tanks Miniatures Game","store_id":4,"store_thumb":"https://www.thegamerules.com/image/cache/catalog/Products%20NEW/World%20of%20Tanks_1-250x250.jpg","price":35.53,"stock":0,"url":"https://www.thegamerules.com/epitrapezia-paixnidia/world-of-tanks-miniatures-game"},{"id":1257,"key":"","name":"World of Tanks: Miniatures Game","transformed_name":"world of tanks  miniatures game","boardgame_name":"World of Tanks Miniatures Game","store_id":8,"store_thumb":"https://static.efantasy.gr/products/148741/148741-0-0500-world-of-tanks-miniatures-game.jpg","price":35.99,"stock":0,"url":"https://www.efantasy.gr/en/products/board-games/148741-world-of-tanks-miniatures-game"}]