[{"id":3885,"cr_date":"2022-04-11T11:16:58+03:00","name":"Snail Sprint (Σαλιγκαροαγώνες)","boardgame_name":"Snail Sprint!","thumb":"https://cf.geekdo-images.com/6r0IOJ6aZFWsuqtGQ_jAxQ__micro/img/UbkRPUrCyZaOjQZGiqGF_qSnL6c=/fit-in/64x64/filters:strip_icc()/pic4533104.jpg","store_id":8,"store_thumb":"https://static.efantasy.gr/products/148671/148671-0-0250-snail-sprint-saligkaroagones.jpg","price":23.39,"stock":false,"url":"https://www.efantasy.gr/en/products/board-games/148671-snail-sprint-%CF%83%CE%B1%CE%BB%CE%B9%CE%B3%CE%BA%CE%B1%CF%81%CE%BF%CE%B1%CE%B3%CF%8E%CE%BD%CE%B5%CF%82","rank":6120}]