[{"cr_date":"2022-02-01T00:00:00+02:00","price":33,"stock":true,"store_id":6},{"cr_date":"2022-02-01T00:00:00+02:00","price":36,"stock":true,"store_id":9},{"cr_date":"2022-01-01T00:00:00+02:00","price":33,"stock":true,"store_id":6},{"cr_date":"2022-01-01T00:00:00+02:00","price":36,"stock":true,"store_id":9},{"cr_date":"2022-03-01T00:00:00+02:00","price":29.69,"stock":true,"store_id":8},{"cr_date":"2022-03-01T00:00:00+02:00","price":33.99,"stock":true,"store_id":15},{"cr_date":"2022-03-01T00:00:00+02:00","price":33,"stock":true,"store_id":6},{"cr_date":"2022-03-01T00:00:00+02:00","price":36,"stock":true,"store_id":9},{"cr_date":"2022-03-01T00:00:00+02:00","price":28,"stock":false,"store_id":3},{"cr_date":"2022-03-01T00:00:00+02:00","price":30.5,"stock":true,"store_id":16},{"cr_date":"2022-04-01T00:00:00+03:00","price":29.69,"stock":false,"store_id":8},{"cr_date":"2022-04-01T00:00:00+03:00","price":33.99,"stock":true,"store_id":15},{"cr_date":"2022-04-01T00:00:00+03:00","price":33,"stock":true,"store_id":6},{"cr_date":"2022-04-01T00:00:00+03:00","price":36,"stock":true,"store_id":9},{"cr_date":"2022-04-01T00:00:00+03:00","price":28,"stock":false,"store_id":3},{"cr_date":"2022-04-01T00:00:00+03:00","price":30.5,"stock":true,"store_id":16}]