[{"id":16073,"key":"","name":"Star Wars Armada: Invisible Hand (Exp)","transformed_name":"star wars armada  invisible hand","boardgame_name":"Star Wars: Armada –  Invisible Hand Expansion Pack","preview":"https://cf.geekdo-images.com/GVWGV9FB6wCUpk9vC3TLpg__micro/img/8w8gylAGkQAok5Y6dwofUb3LOMw=/fit-in/64x64/filters:strip_icc()/pic6027773.png","store_id":4,"store_thumb":"https://www.thegamerules.com/image/cache/catalog/Products%20NEW/Star%20Wars%20Armada%20-%20Invisible%20Hand%201-395x395.jpg","price":70.86,"stock":2,"url":"https://www.thegamerules.com/epitrapezia-paixnidia/star-wars-armada-assault-frigate-mark-ii-exp","ignored":false}]