[{"cr_date":"2022-02-01T00:00:00+02:00","price":64.99,"stock":2,"store_id":4},{"cr_date":"2022-02-01T00:00:00+02:00","price":59.99,"stock":2,"store_id":7},{"cr_date":"2022-02-01T00:00:00+02:00","price":70,"stock":2,"store_id":9},{"cr_date":"2022-01-01T00:00:00+02:00","price":70,"stock":2,"store_id":9},{"cr_date":"2022-01-01T00:00:00+02:00","price":72.99,"stock":2,"store_id":4},{"cr_date":"2022-03-01T00:00:00+02:00","price":59.99,"stock":2,"store_id":7},{"cr_date":"2022-03-01T00:00:00+02:00","price":69.99,"stock":2,"store_id":8},{"cr_date":"2022-03-01T00:00:00+02:00","price":70,"stock":2,"store_id":9},{"cr_date":"2022-03-01T00:00:00+02:00","price":64.99,"stock":2,"store_id":4},{"cr_date":"2022-04-01T00:00:00+03:00","price":59.99,"stock":2,"store_id":7},{"cr_date":"2022-04-01T00:00:00+03:00","price":69.99,"stock":2,"store_id":8},{"cr_date":"2022-04-01T00:00:00+03:00","price":70,"stock":2,"store_id":9},{"cr_date":"2022-04-01T00:00:00+03:00","price":64.99,"stock":2,"store_id":4},{"cr_date":"2022-04-01T00:00:00+03:00","price":60,"stock":0,"store_id":20},{"cr_date":"2022-05-01T00:00:00+03:00","price":60,"stock":0,"store_id":20},{"cr_date":"2022-05-01T00:00:00+03:00","price":59.99,"stock":2,"store_id":7},{"cr_date":"2022-05-01T00:00:00+03:00","price":69.99,"stock":2,"store_id":8},{"cr_date":"2022-05-01T00:00:00+03:00","price":70,"stock":2,"store_id":9},{"cr_date":"2022-05-01T00:00:00+03:00","price":64.99,"stock":2,"store_id":4},{"cr_date":"2022-06-01T00:00:00+03:00","price":59.99,"stock":1,"store_id":7},{"cr_date":"2022-06-01T00:00:00+03:00","price":70,"stock":2,"store_id":9},{"cr_date":"2022-06-01T00:00:00+03:00","price":42.99,"stock":2,"store_id":4},{"cr_date":"2022-06-01T00:00:00+03:00","price":42.74,"stock":0,"store_id":12},{"cr_date":"2022-06-01T00:00:00+03:00","price":45,"stock":0,"store_id":6},{"cr_date":"2022-06-01T00:00:00+03:00","price":39.6,"stock":0,"store_id":21},{"cr_date":"2022-06-01T00:00:00+03:00","price":40.49,"stock":0,"store_id":8},{"cr_date":"2022-06-01T00:00:00+03:00","price":39.59,"stock":2,"store_id":15},{"cr_date":"2022-06-01T00:00:00+03:00","price":39.9,"stock":0,"store_id":18},{"cr_date":"2022-07-01T00:00:00+03:00","price":39.6,"stock":0,"store_id":21},{"cr_date":"2022-07-01T00:00:00+03:00","price":39.9,"stock":2,"store_id":18},{"cr_date":"2022-07-01T00:00:00+03:00","price":70,"stock":2,"store_id":9},{"cr_date":"2022-07-01T00:00:00+03:00","price":42.99,"stock":0,"store_id":4},{"cr_date":"2022-07-01T00:00:00+03:00","price":42.74,"stock":0,"store_id":12},{"cr_date":"2022-07-01T00:00:00+03:00","price":45,"stock":0,"store_id":6},{"cr_date":"2022-07-01T00:00:00+03:00","price":44.99,"stock":2,"store_id":8},{"cr_date":"2022-07-01T00:00:00+03:00","price":39.89,"stock":2,"store_id":15},{"cr_date":"2022-07-01T00:00:00+03:00","price":59.99,"stock":1,"store_id":7},{"cr_date":"2022-08-01T00:00:00+03:00","price":39.6,"stock":0,"store_id":21},{"cr_date":"2022-08-01T00:00:00+03:00","price":41.5,"stock":0,"store_id":18},{"cr_date":"2022-08-01T00:00:00+03:00","price":70,"stock":2,"store_id":9},{"cr_date":"2022-08-01T00:00:00+03:00","price":42.99,"stock":0,"store_id":4},{"cr_date":"2022-08-01T00:00:00+03:00","price":42.74,"stock":0,"store_id":12},{"cr_date":"2022-08-01T00:00:00+03:00","price":45,"stock":0,"store_id":6},{"cr_date":"2022-08-01T00:00:00+03:00","price":40.49,"stock":0,"store_id":8},{"cr_date":"2022-08-01T00:00:00+03:00","price":40.48,"stock":0,"store_id":15},{"cr_date":"2022-08-01T00:00:00+03:00","price":59.99,"stock":1,"store_id":7},{"cr_date":"2022-08-01T00:00:00+03:00","price":44.9,"stock":0,"store_id":2},{"cr_date":"2022-09-01T00:00:00+03:00","price":70,"stock":2,"store_id":9},{"cr_date":"2022-09-01T00:00:00+03:00","price":42.99,"stock":0,"store_id":4},{"cr_date":"2022-09-01T00:00:00+03:00","price":42.74,"stock":0,"store_id":12},{"cr_date":"2022-09-01T00:00:00+03:00","price":45,"stock":0,"store_id":6},{"cr_date":"2022-09-01T00:00:00+03:00","price":39.6,"stock":0,"store_id":21},{"cr_date":"2022-09-01T00:00:00+03:00","price":40.49,"stock":0,"store_id":8},{"cr_date":"2022-09-01T00:00:00+03:00","price":37.94,"stock":0,"store_id":15},{"cr_date":"2022-09-01T00:00:00+03:00","price":37.95,"stock":0,"store_id":18},{"cr_date":"2022-09-01T00:00:00+03:00","price":59.99,"stock":1,"store_id":7},{"cr_date":"2022-09-01T00:00:00+03:00","price":44.9,"stock":0,"store_id":2},{"cr_date":"2022-10-01T00:00:00+03:00","price":70,"stock":2,"store_id":9},{"cr_date":"2022-10-01T00:00:00+03:00","price":42.99,"stock":0,"store_id":4},{"cr_date":"2022-10-01T00:00:00+03:00","price":42.74,"stock":0,"store_id":12},{"cr_date":"2022-10-01T00:00:00+03:00","price":45,"stock":0,"store_id":6},{"cr_date":"2022-10-01T00:00:00+03:00","price":39.6,"stock":0,"store_id":21},{"cr_date":"2022-10-01T00:00:00+03:00","price":40.49,"stock":0,"store_id":8},{"cr_date":"2022-10-01T00:00:00+03:00","price":37.94,"stock":0,"store_id":15},{"cr_date":"2022-10-01T00:00:00+03:00","price":35.6,"stock":0,"store_id":18},{"cr_date":"2022-10-01T00:00:00+03:00","price":59.99,"stock":1,"store_id":7},{"cr_date":"2022-10-01T00:00:00+03:00","price":44.9,"stock":0,"store_id":2},{"cr_date":"2022-11-01T00:00:00+02:00","price":70,"stock":2,"store_id":9},{"cr_date":"2022-11-01T00:00:00+02:00","price":42.99,"stock":2,"store_id":4},{"cr_date":"2022-11-01T00:00:00+02:00","price":42.74,"stock":0,"store_id":12},{"cr_date":"2022-11-01T00:00:00+02:00","price":45,"stock":0,"store_id":6},{"cr_date":"2022-11-01T00:00:00+02:00","price":40.49,"stock":0,"store_id":8},{"cr_date":"2022-11-01T00:00:00+02:00","price":37.94,"stock":2,"store_id":15},{"cr_date":"2022-11-01T00:00:00+02:00","price":59.99,"stock":1,"store_id":7},{"cr_date":"2022-11-01T00:00:00+02:00","price":44.9,"stock":0,"store_id":2},{"cr_date":"2022-11-01T00:00:00+02:00","price":45,"stock":0,"store_id":25},{"cr_date":"2022-11-01T00:00:00+02:00","price":39.99,"stock":0,"store_id":26}]