[{"id":14618,"key":"","name":"Star Wars Legion: Imperial Shoretroopers Unit Expansion","transformed_name":"star wars legion  imperial shoretroopers unit  ","boardgame_name":"Star Wars: Legion – Imperial Shoretroopers Unit Expansion","preview":"https://cf.geekdo-images.com/RDvi0IxcTuPoUDL_wyQSYQ__micro/img/kDAibI8pMFTe2jG50yvMX8dvhbU=/fit-in/64x64/filters:strip_icc()/pic4699670.jpg","store_id":3,"store_thumb":"","price":31.99,"stock":2,"url":"https://www.mystery-bay.com/product-page/star-wars-legion-imperial-shoretroopers-unit-expansion"}]