[{"id":18455,"name":"SMASH UP : THAT '70S EXPANSION","transformed_name":"smash up   that '70s  ","boardgame_name":"Smash Up: That '70s Expansion","store_id":22,"store_thumb":"https://ti.gameexplorers.gr/smash-up-that-70s-expansion.jpg","price":19.9,"stock":0,"url":"https://www.gameexplorers.gr/6066968/smash-up-that-70s-expansion.html"},{"id":4768,"name":"Smash Up: That '70s Expansion","transformed_name":"smash up  that '70s  ","boardgame_name":"Smash Up: That '70s Expansion","store_id":4,"store_thumb":"https://www.thegamerules.com/image/cache/catalog/product/smashupthat70sexpansionbox-250x250.png","price":21.06,"stock":0,"url":"https://www.thegamerules.com/epitrapezia-paixnidia/smash-up-that-70s-expansion-detail"},{"id":2170,"name":"Smash Up: That 70s","transformed_name":"smash up  that 70s","boardgame_name":"Smash Up: That '70s Expansion","store_id":8,"store_thumb":"https://static.efantasy.gr/products/117127/117127-0-0500-smash-up-that-70s.jpg","price":24.99,"stock":2,"url":"https://www.efantasy.gr/en/products/board-games/117127-smash-up-that-70s"},{"id":9506,"name":"SMASH UP : THAT '70s EXPANSION","transformed_name":"smash up   that '70s  ","boardgame_name":"Smash Up: That '70s Expansion","store_id":9,"store_thumb":"https://kaissa.gr/pub/media/catalog/product/cache/40839b2953d2ba4cdf07b38b981ce6be/s/m/smash-up-that-_70s-expansion-box.png","price":25,"stock":0,"url":"https://kaissagames.com/b2c_gr/smash-up-that-70s-expansion.html"},{"id":9204,"name":"Smash Up: That '70s Expansion","transformed_name":"smash up  that '70s  ","boardgame_name":"Smash Up: That '70s Expansion","store_id":6,"store_thumb":"https://www.kaissa.eu/var/thumbs/15260504424e338b39f70aa1ed95b13238803bfdd1_e_shop_products_25896_photo_260_240__s_____.jpg","price":25,"stock":2,"url":"https://www.kaissa.eu/product/smash-up-that-70s-expansion"}]