[{"id":17902,"key":"","name":"DOMINION: NOCTURNE","transformed_name":"dominion  nocturne","boardgame_name":"Dominion: Nocturne","store_id":12,"store_thumb":"https://www.politeianet.gr/components/com_virtuemart/themes/vm_mynxx/images/noimage.gif","price":38,"stock":0,"url":"https://www.politeianet.gr/books/rio-grande-games-dominion-nocturne-334123"},{"id":2259,"key":"","name":"Dominion: Nocturne","transformed_name":"dominion  nocturne","boardgame_name":"Dominion: Nocturne","store_id":9,"store_thumb":"https://kaissa.gr/pub/media/catalog/product/cache/40839b2953d2ba4cdf07b38b981ce6be/p/i/pic3677538.jpg","price":40,"stock":0,"url":"https://kaissagames.com/b2c_gr/dominion-nocturne.html"},{"id":1352,"key":"","name":"Dominion: Nocturne (Expansion)","transformed_name":"dominion  nocturne","boardgame_name":"Dominion: Nocturne","store_id":8,"store_thumb":"https://static.efantasy.gr/products/136423/136423-0-0500-dominion-nocturne-expansion.jpg","price":44.99,"stock":2,"url":"https://www.efantasy.gr/en/products/board-games/136423-dominion-nocturne-expansion"},{"id":1803,"key":"","name":"Dominion: Nocturne","transformed_name":"dominion  nocturne","boardgame_name":"Dominion: Nocturne","store_id":6,"store_thumb":"https://www.kaissa.eu/var/thumbs/1639763711a2bb64600a0c990782384c158a9d1ec0_everdell__260_240__s_____.jpg","price":45,"stock":0,"url":"https://www.kaissa.eu/product/dominion-nocturne"}]