[{"id":1439,"name":"Santorini","transformed_name":"santorini","boardgame_name":"Santorini","store_id":8,"store_thumb":"https://static.efantasy.gr/products/100395/100395-0-0500-santorini.jpg","price":19.99,"stock":2,"url":"https://www.efantasy.gr/en/products/board-games/100395-santorini"},{"id":13822,"name":"Santorini","transformed_name":"santorini","boardgame_name":"Santorini","store_id":4,"store_thumb":"https://www.thegamerules.com/image/cache/catalog/Products%20NEW/Santorini%20post-250x250.jpg","price":19.99,"stock":2,"url":"https://www.thegamerules.com/epitrapezia-paixnidia?product_id=26190"},{"id":14984,"name":"Santorini","transformed_name":"santorini","boardgame_name":"Santorini","store_id":3,"store_thumb":"https://static.wixstatic.com/media/9dcd7c_2d73bb332e4347cabcd0e937c6dcb646~mv2.jpg/v1/fill/w_100,h_100,al_c,q_80,usm_0.66_1.00_0.01/9dcd7c_2d73bb332e4347cabcd0e937c6dcb646~mv2.jpg","price":35,"stock":0,"url":"https://www.mystery-bay.com/product-page/santorini"},{"id":12194,"name":"Santorini","transformed_name":"santorini","boardgame_name":"Santorini","store_id":10,"store_thumb":"https://meepleonboard.gr/wp-content/uploads/2019/06/Santorini-510x600.png","price":38,"stock":2,"url":"https://meepleonboard.gr/shop/board-games/strategy/santorini/"}]