[{"id":14652,"key":"","name":"Everdell Bellfaire (exp)","transformed_name":"everdell bellfaire","boardgame_name":"Everdell: Bellfaire","store_id":3,"store_thumb":"","price":34,"stock":2,"url":"https://www.mystery-bay.com/product-page/everdell-bellfaire"},{"id":5175,"key":"","name":"Everdell: Bellfaire","transformed_name":"everdell  bellfaire","boardgame_name":"Everdell: Bellfaire","store_id":10,"store_thumb":"https://meepleonboard.gr/wp-content/uploads/2021/06/design-d2a50f8c-6998-4736-b1fe-d53bf4ad59b8-19-510x612.png","price":37,"stock":2,"url":"https://meepleonboard.gr/shop/board-games/strategy/everdell-bellfaire/"},{"id":9764,"key":"","name":"Everdell: Bellfaire (Exp)","transformed_name":"everdell  bellfaire","boardgame_name":"Everdell: Bellfaire","store_id":4,"store_thumb":"https://www.thegamerules.com/image/cache/catalog/product/everdellbellfaireexpbox-250x250.png","price":38.1,"stock":2,"url":"https://www.thegamerules.com/epitrapezia-paixnidia/everdell-bellfaire-exp-detail"},{"id":7136,"key":"","name":"Everdell: Bellfaire","transformed_name":"everdell  bellfaire","boardgame_name":"Everdell: Bellfaire","store_id":5,"store_thumb":"https://store.v-games.gr/wp-content/uploads/2021/06/Everdell-Bellfaire-e1623957629670-324x324.png","price":41.5,"stock":2,"url":"https://store.v-games.gr/product/everdell-bellfaire/"},{"id":5755,"key":"","name":"Everdell: Bellfaire","transformed_name":"everdell  bellfaire","boardgame_name":"Everdell: Bellfaire","store_id":6,"store_thumb":"https://www.kaissa.eu/var/thumbs/16022423259f39c070eb1ed0caefc5bc00a924ea16_e_shop_products_29370_photo_260_240__s_____.jpg","price":44,"stock":2,"url":"https://www.kaissa.eu/product/everdell-bellfaire"},{"id":6742,"key":"","name":"Everdell: Bellfaire","transformed_name":"everdell  bellfaire","boardgame_name":"Everdell: Bellfaire","store_id":9,"store_thumb":"https://kaissa.gr/pub/media/catalog/product/cache/40839b2953d2ba4cdf07b38b981ce6be/e/v/everdellbellfaireexpbox-550x550.png","price":44,"stock":2,"url":"https://kaissagames.com/b2c_gr/everdell-bellfaire.html"},{"id":4072,"key":"","name":"Everdell: Bellfaire (Expansion)","transformed_name":"everdell  bellfaire","boardgame_name":"Everdell: Bellfaire","store_id":8,"store_thumb":"https://static.efantasy.gr/products/155343/155343-0-0500-everdell-bellfaire-expansion.jpg","price":44.99,"stock":2,"url":"https://www.efantasy.gr/en/products/board-games/155343-everdell-bellfaire-expansion"}]