[{"id":16439,"key":"","name":"Επιτραπέζιο Η Λίμνη Με Τα Βατραχάκια","transformed_name":" η λίμνη με τα βατραχάκια","boardgame_name":"Hooop!","store_id":18,"store_thumb":"https://www.gamescom.gr/images/thumbnails/230/230/detailed/12/12_e5sp-a8.jpg","price":15.8,"stock":0,"url":"https://www.gamescom.gr/epitrapezia-el/epitrapezia/paidika/epitrapezio-i-limni-me-ta-batraxakia-5205444112141.html"},{"id":18227,"key":"","name":"Κάισσα Επιτραπέζιο Η Λίμνη Με Τα Βατραχάκια","transformed_name":"  η λίμνη με τα βατραχάκια","boardgame_name":"Hooop!","store_id":21,"store_thumb":"https://1132140367.rsc.cdn77.org/156189-home_default/kaissa-epitrapezio-i-limni-me-ta-vatrachakia.jpg","price":17.6,"stock":0,"url":"https://xrysoftero.gr/epitrapezia-paixnidia/479367-kaissa-epitrapezio-i-limni-me-ta-vatrachakia"},{"id":6138,"key":"","name":"Η Λίμνη με τα Βατραχάκια","transformed_name":"η λίμνη με τα βατραχάκια","boardgame_name":"Hooop!","store_id":4,"store_thumb":"https://www.thegamerules.com/image/cache/catalog/product/ilimnimetabatraxakiabox-250x250.png","price":17.9,"stock":0,"url":"https://www.thegamerules.com/epitrapezia-paixnidia/η-λίμνη-με-τα-βατραχάκια-detail"},{"id":19096,"key":"","name":"Η Λίμνη Με Τα Βατραχάκια","transformed_name":"η λίμνη με τα βατραχάκια","boardgame_name":"Hooop!","store_id":23,"store_thumb":"https://cdn.shopify.com/s/files/1/0571/7075/5773/products/1_578b6b38-2e2f-4f83-9e7c-3365a7e9c117.jpg?v=1632578794","price":19.99,"stock":0,"url":"https://hobbytheory.myshopify.com/products/η-λίμνη-με-τα-βατραχάκια"},{"id":21117,"key":"","name":"Η Λίμνη Με Τα Βατραχάκια","transformed_name":"η λίμνη με τα βατραχάκια","boardgame_name":"Hooop!","store_id":25,"store_thumb":"https://avalongames.gr/image/cache/catalog/data/KA112141_Λίμνη_Βατραχάκια-250x250w.jpeg","price":19.99,"stock":0,"url":"https://avalongames.gr/index.php?route=product/product&path=59&product_id=2298&limit=100"},{"id":1512,"key":"","name":"Η Λίμνη με τα Βατραχάκια","transformed_name":"η λίμνη με τα βατραχάκια","boardgame_name":"Hooop!","store_id":8,"store_thumb":"https://static.efantasy.gr/products/87413/87413-0-0500-i-limni-me-ta-batraxakia.jpg","price":19.99,"stock":2,"url":"https://www.efantasy.gr/en/products/board-games/87413-%CE%B7-%CE%BB%CE%AF%CE%BC%CE%BD%CE%B7-%CE%BC%CE%B5-%CF%84%CE%B1-%CE%B2%CE%B1%CF%84%CF%81%CE%B1%CF%87%CE%AC%CE%BA%CE%B9%CE%B1"},{"id":24232,"key":"","name":"Η Λίμνη με τα Βατραχάκια","transformed_name":"η λίμνη με τα βατραχάκια","boardgame_name":"Hooop!","store_id":28,"store_thumb":"https://www.fantasy-shop.gr/images/thumbnails/240/240/detailed/10/00008204.jpg","price":19.99,"stock":0,"url":"https://www.fantasy-shop.gr/product-20737.html"},{"id":15949,"key":"","name":"Η Λίμνη με τα Βατραχάκια","transformed_name":"η λίμνη με τα βατραχάκια","boardgame_name":"Hooop!","store_id":6,"store_thumb":"https://www.kaissa.eu/var/thumbs/14797594537b8727f90a8f1fd98bbb97652c61b025_e_shop_products_23791_photo_260_240__s_____.jpg","price":20,"stock":2,"url":"https://www.kaissa.eu/product/i-limni-me-ta-vatraxakia"}]