{"key":"","transformed_name":"a game of thrones  2nd edition   called to arms","boardgame_id":196619,"boardgame_name":"A Game of Thrones: The Card Game (Second Edition) - Called to Arms","preview":"https://cf.geekdo-images.com/RzWA0tdD2IoN06B0c5mzNA__micro/img/i4GLmel_DBhNMmzfbThW2UkM8No=/fit-in/64x64/filters:strip_icc()/pic2955402.png","ignored":false,"images":["https://cf.geekdo-images.com/RzWA0tdD2IoN06B0c5mzNA__micro/img/i4GLmel_DBhNMmzfbThW2UkM8No=/fit-in/64x64/filters:strip_icc()/pic2955402.png","https://www.thegamerules.com/image/cache/transparent-395x395.png"]}