[{"cr_date":"2022-08-01T00:00:00+03:00","price":150,"stock":2,"store_id":9},{"cr_date":"2022-09-01T00:00:00+03:00","price":150,"stock":2,"store_id":9},{"cr_date":"2022-10-01T00:00:00+03:00","price":150,"stock":2,"store_id":9},{"cr_date":"2022-11-01T00:00:00+02:00","price":150,"stock":0,"store_id":9},{"cr_date":"2022-11-01T00:00:00+02:00","price":134.99,"stock":0,"store_id":8},{"cr_date":"2022-11-01T00:00:00+02:00","price":167.9,"stock":0,"store_id":3},{"cr_date":"2022-12-01T00:00:00+02:00","price":150,"stock":0,"store_id":9},{"cr_date":"2022-12-01T00:00:00+02:00","price":167.9,"stock":0,"store_id":3},{"cr_date":"2022-12-01T00:00:00+02:00","price":149.99,"stock":2,"store_id":8},{"cr_date":"2023-03-01T00:00:00+02:00","price":149.99,"stock":2,"store_id":8},{"cr_date":"2023-03-01T00:00:00+02:00","price":167.9,"stock":0,"store_id":3},{"cr_date":"2023-03-01T00:00:00+02:00","price":100,"stock":0,"store_id":9},{"cr_date":"2023-03-01T00:00:00+02:00","price":115.86,"stock":0,"store_id":17},{"cr_date":"2023-04-01T00:00:00+03:00","price":100,"stock":0,"store_id":9},{"cr_date":"2023-04-01T00:00:00+03:00","price":167.9,"stock":0,"store_id":3},{"cr_date":"2023-04-01T00:00:00+03:00","price":149.99,"stock":2,"store_id":8},{"cr_date":"2023-04-01T00:00:00+03:00","price":134.32,"stock":0,"store_id":3}]