[{"id":13800,"key":"","name":"Cosmic Encounter 42nd Anniversary Ed.","transformed_name":"cosmic encounter 42nd anniversary ed.","boardgame_name":"Cosmic Encounter: 42nd Anniversary Edition","preview":"https://cf.geekdo-images.com/-pnk2c0HTQQrhqRjjG835Q__micro/img/SpomkhFVAgR6IB8sUBtl4iCL_bI=/fit-in/64x64/filters:strip_icc()/pic4243113.jpg","store_id":5,"store_thumb":"","price":57.5,"stock":2,"url":"https://store.v-games.gr/product/cosmic-encounter/","ignored":false},{"id":14828,"key":"","name":"Cosmic Encounter 42nd Anniversary Edition","transformed_name":"cosmic encounter 42nd anniversary edition","boardgame_name":"Cosmic Encounter: 42nd Anniversary Edition","preview":"https://cf.geekdo-images.com/-pnk2c0HTQQrhqRjjG835Q__micro/img/SpomkhFVAgR6IB8sUBtl4iCL_bI=/fit-in/64x64/filters:strip_icc()/pic4243113.jpg","store_id":3,"store_thumb":"https://static.wixstatic.com/media/9dcd7c_4f2d0931395041928fd52196f445bd1f~mv2.png","price":58,"stock":2,"url":"https://www.mystery-bay.com/product-page/cosmic-encounter-42nd-anniversary-edition","ignored":false}]