[{"cr_date":"2022-02-01T00:00:00+02:00","price":20,"stock":2,"store_id":6},{"cr_date":"2022-02-01T00:00:00+02:00","price":12,"stock":2,"store_id":9},{"cr_date":"2022-01-01T00:00:00+02:00","price":12,"stock":2,"store_id":9},{"cr_date":"2022-01-01T00:00:00+02:00","price":20,"stock":2,"store_id":6},{"cr_date":"2022-03-01T00:00:00+02:00","price":12,"stock":2,"store_id":9},{"cr_date":"2022-03-01T00:00:00+02:00","price":11.69,"stock":0,"store_id":8},{"cr_date":"2022-03-01T00:00:00+02:00","price":12.23,"stock":0,"store_id":4},{"cr_date":"2022-03-01T00:00:00+02:00","price":11.99,"stock":0,"store_id":15},{"cr_date":"2022-03-01T00:00:00+02:00","price":20,"stock":2,"store_id":6},{"cr_date":"2022-04-01T00:00:00+03:00","price":10.29,"stock":0,"store_id":8},{"cr_date":"2022-04-01T00:00:00+03:00","price":12.23,"stock":0,"store_id":4},{"cr_date":"2022-04-01T00:00:00+03:00","price":11.99,"stock":0,"store_id":15},{"cr_date":"2022-04-01T00:00:00+03:00","price":13,"stock":0,"store_id":6},{"cr_date":"2022-04-01T00:00:00+03:00","price":12,"stock":2,"store_id":9},{"cr_date":"2022-04-01T00:00:00+03:00","price":10.3,"stock":0,"store_id":18},{"cr_date":"2022-04-01T00:00:00+03:00","price":11.44,"stock":0,"store_id":21},{"cr_date":"2022-04-01T00:00:00+03:00","price":13.25,"stock":0,"store_id":22},{"cr_date":"2022-04-01T00:00:00+03:00","price":12.99,"stock":0,"store_id":23},{"cr_date":"2022-05-01T00:00:00+03:00","price":12.99,"stock":0,"store_id":24},{"cr_date":"2022-05-01T00:00:00+03:00","price":10.3,"stock":0,"store_id":18},{"cr_date":"2022-05-01T00:00:00+03:00","price":12.99,"stock":0,"store_id":23},{"cr_date":"2022-05-01T00:00:00+03:00","price":10.29,"stock":0,"store_id":8},{"cr_date":"2022-05-01T00:00:00+03:00","price":12.23,"stock":2,"store_id":4},{"cr_date":"2022-05-01T00:00:00+03:00","price":11.99,"stock":0,"store_id":15},{"cr_date":"2022-05-01T00:00:00+03:00","price":13,"stock":0,"store_id":6},{"cr_date":"2022-05-01T00:00:00+03:00","price":12,"stock":2,"store_id":9},{"cr_date":"2022-05-01T00:00:00+03:00","price":11.44,"stock":0,"store_id":21},{"cr_date":"2022-05-01T00:00:00+03:00","price":13.25,"stock":0,"store_id":22},{"cr_date":"2022-05-01T00:00:00+03:00","price":12.99,"stock":0,"store_id":25},{"cr_date":"2022-06-01T00:00:00+03:00","price":10.29,"stock":0,"store_id":8},{"cr_date":"2022-06-01T00:00:00+03:00","price":12.23,"stock":2,"store_id":4},{"cr_date":"2022-06-01T00:00:00+03:00","price":11.99,"stock":0,"store_id":15},{"cr_date":"2022-06-01T00:00:00+03:00","price":13,"stock":0,"store_id":6},{"cr_date":"2022-06-01T00:00:00+03:00","price":12,"stock":2,"store_id":9},{"cr_date":"2022-06-01T00:00:00+03:00","price":10.3,"stock":0,"store_id":18},{"cr_date":"2022-06-01T00:00:00+03:00","price":11.44,"stock":0,"store_id":21},{"cr_date":"2022-06-01T00:00:00+03:00","price":13.25,"stock":0,"store_id":22},{"cr_date":"2022-06-01T00:00:00+03:00","price":12.99,"stock":0,"store_id":23},{"cr_date":"2022-06-01T00:00:00+03:00","price":12.99,"stock":0,"store_id":24},{"cr_date":"2022-06-01T00:00:00+03:00","price":12.99,"stock":0,"store_id":25},{"cr_date":"2022-07-01T00:00:00+03:00","price":12.23,"stock":2,"store_id":4},{"cr_date":"2022-07-01T00:00:00+03:00","price":11.99,"stock":0,"store_id":15},{"cr_date":"2022-07-01T00:00:00+03:00","price":13,"stock":0,"store_id":6},{"cr_date":"2022-07-01T00:00:00+03:00","price":12,"stock":2,"store_id":9},{"cr_date":"2022-07-01T00:00:00+03:00","price":10.3,"stock":0,"store_id":18},{"cr_date":"2022-07-01T00:00:00+03:00","price":11.44,"stock":0,"store_id":21},{"cr_date":"2022-07-01T00:00:00+03:00","price":13.25,"stock":0,"store_id":22},{"cr_date":"2022-07-01T00:00:00+03:00","price":12.99,"stock":0,"store_id":23},{"cr_date":"2022-07-01T00:00:00+03:00","price":12.99,"stock":0,"store_id":24},{"cr_date":"2022-07-01T00:00:00+03:00","price":12.99,"stock":0,"store_id":25},{"cr_date":"2022-07-01T00:00:00+03:00","price":11.69,"stock":0,"store_id":8},{"cr_date":"2022-08-01T00:00:00+03:00","price":10.3,"stock":0,"store_id":18},{"cr_date":"2022-08-01T00:00:00+03:00","price":13,"stock":0,"store_id":21},{"cr_date":"2022-08-01T00:00:00+03:00","price":12.23,"stock":2,"store_id":4},{"cr_date":"2022-08-01T00:00:00+03:00","price":11.99,"stock":0,"store_id":15},{"cr_date":"2022-08-01T00:00:00+03:00","price":13,"stock":0,"store_id":6},{"cr_date":"2022-08-01T00:00:00+03:00","price":12,"stock":2,"store_id":9},{"cr_date":"2022-08-01T00:00:00+03:00","price":13.25,"stock":0,"store_id":22},{"cr_date":"2022-08-01T00:00:00+03:00","price":12.99,"stock":0,"store_id":23},{"cr_date":"2022-08-01T00:00:00+03:00","price":12.99,"stock":0,"store_id":24},{"cr_date":"2022-08-01T00:00:00+03:00","price":12.99,"stock":0,"store_id":25},{"cr_date":"2022-08-01T00:00:00+03:00","price":11.69,"stock":0,"store_id":8},{"cr_date":"2022-09-01T00:00:00+03:00","price":12.23,"stock":2,"store_id":4},{"cr_date":"2022-09-01T00:00:00+03:00","price":11.99,"stock":0,"store_id":15},{"cr_date":"2022-09-01T00:00:00+03:00","price":13,"stock":0,"store_id":6},{"cr_date":"2022-09-01T00:00:00+03:00","price":12,"stock":2,"store_id":9},{"cr_date":"2022-09-01T00:00:00+03:00","price":13.25,"stock":0,"store_id":22},{"cr_date":"2022-09-01T00:00:00+03:00","price":12.99,"stock":0,"store_id":23},{"cr_date":"2022-09-01T00:00:00+03:00","price":12.99,"stock":0,"store_id":24},{"cr_date":"2022-09-01T00:00:00+03:00","price":12.99,"stock":0,"store_id":25},{"cr_date":"2022-09-01T00:00:00+03:00","price":11.69,"stock":0,"store_id":8},{"cr_date":"2022-09-01T00:00:00+03:00","price":11.44,"stock":0,"store_id":21},{"cr_date":"2022-09-01T00:00:00+03:00","price":11,"stock":0,"store_id":18}]