[{"id":9490,"key":"","name":"ALADDIN AND THE MAGIC LAMP","transformed_name":"aladdin and the magic lamp","boardgame_name":"Aladdin and the Magic Lamp","preview":"https://cf.geekdo-images.com/d-n9-d_SuePc9cE586BIiQ__micro/img/Ubx-5sJRenDOOr5uTl9kpkNRf4I=/fit-in/64x64/filters:strip_icc()/pic1007006.jpg","store_id":9,"store_thumb":"https://kaissa.gr/pub/media/catalog/product/cache/40839b2953d2ba4cdf07b38b981ce6be/p/i/pic3105221.jpg","price":15,"stock":2,"url":"https://kaissagames.com/b2c_gr/aladdin-and-the-magic-lamp.html"},{"id":22547,"key":"","name":"Aladdin and the Magic Lamp","transformed_name":"aladdin and the magic lamp","boardgame_name":"Aladdin and the Magic Lamp","preview":"https://cf.geekdo-images.com/d-n9-d_SuePc9cE586BIiQ__micro/img/Ubx-5sJRenDOOr5uTl9kpkNRf4I=/fit-in/64x64/filters:strip_icc()/pic1007006.jpg","store_id":7,"store_thumb":"https://meeple-planet.com/wp-content/uploads/2019/05/box-15-200x200.jpg","price":22.5,"stock":0,"url":"https://meeple-planet.com/aladdin-and-the-magic-lamp/"}]