[{"id":12377,"key":"","name":"Princess Legend","transformed_name":"princess legend","boardgame_name":"Campaigns & Commanders: The King's Officers – The British and Italian Armies 1940-1944: A Panzer Grenadier Campaign Book","preview":"https://cf.geekdo-images.com/hk0jxNcNpZOwxZ_nob_ixQ__micro/img/Lf2Ai8qvkCjWPQZaWTxRjtKiVPY=/fit-in/64x64/filters:strip_icc()/pic677313.jpg","store_id":5,"store_thumb":"","price":12.5,"stock":0,"url":"https://store.v-games.gr/product/princess-legend/","ignored":false}]